db_engines/constants.py
db_engines/mongodb_engine.py
db_engines/mongodb_utils.py
db_engines/mysql_engine.py
db_engines/mysql_utils.py
db_engines-0.1.11.dist-info/METADATA
db_engines-0.1.11.dist-info/WHEEL
db_engines-0.1.11.dist-info/RECORD
